{
  "id": "uk/modularity-deployment",
  "title": "Модульність та Розгортання",
  "description": "GeniVerse побудований на модульній архітектурі, яка дозволяє гнучкі варіанти розгортання, від хмарного SaaS до локальних встановлень та гібридних конфігурацій. Ця модульність дозволяє установам вибрати модель розгортання, яка найкраще відповідає їх потребам, вимогам безпеки та можливостям інфраструктури.",
  "source": "@site/docs/uk/modularity-deployment.md",
  "sourceDirName": "uk",
  "slug": "/uk/modularity-deployment",
  "permalink": "/uk/uk/modularity-deployment",
  "draft": false,
  "unlisted": false,
  "tags": [],
  "version": "current",
  "frontMatter": {}
}